{"cameraMode":{"drawMode":0,"name":"Shaded","section":"Shading Mode"},"sceneLighting":false,"audioPlay":false,"sceneViewState":{"m_AlwaysRefresh":false,"showFog":true,"showSkybox":false,"showFlares":true,"showImageEffects":true,"showParticleSystems":true,"showVisualEffectGraphs":true,"m_FxEnabled":true},"in2DMode":false,"pivot":{"x":0.4075603485107422,"y":-0.8349528312683106,"z":-1.0625817775726319},"rotation":{"x":-0.00034547661198303103,"y":-0.9994972944259644,"z":-0.010188239626586438,"w":0.033884625881910327},"size":12.22568416595459,"orthographic":false}